latex_slides/__init__.py
latex_slides/classes.py
latex_slides-0.0.1.dist-info/LICENSE
latex_slides-0.0.1.dist-info/METADATA
latex_slides-0.0.1.dist-info/WHEEL
latex_slides-0.0.1.dist-info/top_level.txt
latex_slides-0.0.1.dist-info/RECORD
