Metadata-Version: 2.1
Name: latex-slides
Version: 0.0.1
Summary: A package to make slides for repeating samples.
Home-page: https://github.com/saeid-h/latex_slide_maker
Author: Saeid Hosseinipoor
Author-email: shossei1@stevens.edu
License: UNKNOWN
Platform: UNKNOWN
Classifier: Programming Language :: Python :: 3
Classifier: License :: OSI Approved :: MIT License
Classifier: Operating System :: OS Independent
Requires-Python: >=3.5
